[
  {
    "id": "46a84838-1d2d-40d3-88d8-30fa1d15e3fc",
    "specie": {
      "id": "squirtle",
      "nome": "Squirtle",
      "tipi": [
        {
          "nome": "Acqua"
        }
      ],
      "pvBase": 44,
      "attaccoBase": 48,
      "difesaBase": 65,
      "velocitaBase": 43,
      "mosseDisponibili": []
    },
    "livello": 5,
    "esperienza": 0,
    "pvAttuali": 44,
    "mosseApprese": [
      {
        "nome": "Tackle",
        "tipo": {
          "nome": "Normale"
        },
        "potenza": 40,
        "precisione": 100,
        "categoria": "FISICA"
      },
      {
        "nome": "Pistolacqua",
        "tipo": {
          "nome": "Acqua"
        },
        "potenza": 40,
        "precisione": 100,
        "categoria": "SPECIALE"
      }
    ]
  },
  {
    "id": "cdb8719a-ecc0-4e5a-8619-3e775ba3c9ba",
    "specie": {
      "id": "squirtle",
      "nome": "Squirtle",
      "tipi": [
        {
          "nome": "Acqua"
        }
      ],
      "pvBase": 44,
      "attaccoBase": 48,
      "difesaBase": 65,
      "velocitaBase": 43,
      "mosseDisponibili": []
    },
    "livello": 5,
    "esperienza": 0,
    "pvAttuali": 44,
    "mosseApprese": [
      {
        "nome": "Tackle",
        "tipo": {
          "nome": "Normale"
        },
        "potenza": 40,
        "precisione": 100,
        "categoria": "FISICA"
      },
      {
        "nome": "Pistolacqua",
        "tipo": {
          "nome": "Acqua"
        },
        "potenza": 40,
        "precisione": 100,
        "categoria": "SPECIALE"
      }
    ]
  },
  {
    "id": "27ba9d1d-a193-41e8-907a-a08bbe8f7970",
    "specie": {
      "id": "squirtle",
      "nome": "Squirtle",
      "tipi": [
        {
          "nome": "Acqua"
        }
      ],
      "pvBase": 44,
      "attaccoBase": 48,
      "difesaBase": 65,
      "velocitaBase": 43,
      "mosseDisponibili": []
    },
    "livello": 5,
    "esperienza": 0,
    "pvAttuali": 44,
    "mosseApprese": [
      {
        "nome": "Tackle",
        "tipo": {
          "nome": "Normale"
        },
        "potenza": 40,
        "precisione": 100,
        "categoria": "FISICA"
      },
      {
        "nome": "Pistolacqua",
        "tipo": {
          "nome": "Acqua"
        },
        "potenza": 40,
        "precisione": 100,
        "categoria": "SPECIALE"
      }
    ]
  },
  {
    "id": "57966b44-b898-4b89-b9db-d19f36571972",
    "specie": {
      "id": "bulbasaur",
      "nome": "Bulbasaur",
      "tipi": [
        {
          "nome": "Erba"
        }
      ],
      "pvBase": 45,
      "attaccoBase": 49,
      "difesaBase": 49,
      "velocitaBase": 45,
      "mosseDisponibili": []
    },
    "livello": 5,
    "esperienza": 0,
    "pvAttuali": 45,
    "mosseApprese": [
      {
        "nome": "Tackle",
        "tipo": {
          "nome": "Normale"
        },
        "potenza": 40,
        "precisione": 100,
        "categoria": "FISICA"
      },
      {
        "nome": "FogliaLama",
        "tipo": {
          "nome": "Erba"
        },
        "potenza": 55,
        "precisione": 95,
        "categoria": "SPECIALE"
      }
    ]
  },
  {
    "id": "6b1ec40f-8c08-4dd0-a39c-c9040d167aaa",
    "specie": {
      "id": "squirtle",
      "nome": "Squirtle",
      "tipi": [
        {
          "nome": "Acqua"
        }
      ],
      "pvBase": 44,
      "attaccoBase": 48,
      "difesaBase": 65,
      "velocitaBase": 43,
      "mosseDisponibili": []
    },
    "livello": 5,
    "esperienza": 0,
    "pvAttuali": 44,
    "mosseApprese": [
      {
        "nome": "Tackle",
        "tipo": {
          "nome": "Normale"
        },
        "potenza": 40,
        "precisione": 100,
        "categoria": "FISICA"
      },
      {
        "nome": "Pistolacqua",
        "tipo": {
          "nome": "Acqua"
        },
        "potenza": 40,
        "precisione": 100,
        "categoria": "SPECIALE"
      }
    ]
  },
  {
    "id": "91a35232-7aa0-4197-84f5-1a0a89033ddd",
    "specie": {
      "id": "squirtle",
      "nome": "Squirtle",
      "tipi": [
        {
          "nome": "Acqua"
        }
      ],
      "pvBase": 44,
      "attaccoBase": 48,
      "difesaBase": 65,
      "velocitaBase": 43,
      "mosseDisponibili": []
    },
    "livello": 5,
    "esperienza": 0,
    "pvAttuali": 44,
    "mosseApprese": [
      {
        "nome": "Tackle",
        "tipo": {
          "nome": "Normale"
        },
        "potenza": 40,
        "precisione": 100,
        "categoria": "FISICA"
      },
      {
        "nome": "Pistolacqua",
        "tipo": {
          "nome": "Acqua"
        },
        "potenza": 40,
        "precisione": 100,
        "categoria": "SPECIALE"
      }
    ]
  },
  {
    "id": "3300acd6-a7c0-41ba-a0b7-fa6b77b80e0a",
    "specie": {
      "id": "charmander",
      "nome": "Charmander",
      "tipi": [
        {
          "nome": "Fuoco"
        }
      ],
      "pvBase": 39,
      "attaccoBase": 52,
      "difesaBase": 43,
      "velocitaBase": 65,
      "mosseDisponibili": []
    },
    "livello": 5,
    "esperienza": 0,
    "pvAttuali": 39,
    "mosseApprese": [
      {
        "nome": "Graffio",
        "tipo": {
          "nome": "Normale"
        },
        "potenza": 40,
        "precisione": 100,
        "categoria": "FISICA"
      },
      {
        "nome": "Fiammata",
        "tipo": {
          "nome": "Fuoco"
        },
        "potenza": 90,
        "precisione": 100,
        "categoria": "SPECIALE"
      }
    ]
  },
  {
    "id": "ca67c9c4-cf8a-4852-b542-77b75fb50a80",
    "specie": {
      "id": "charmander",
      "nome": "Charmander",
      "tipi": [
        {
          "nome": "Fuoco"
        }
      ],
      "pvBase": 39,
      "attaccoBase": 52,
      "difesaBase": 43,
      "velocitaBase": 65,
      "mosseDisponibili": []
    },
    "livello": 5,
    "esperienza": 0,
    "pvAttuali": 39,
    "mosseApprese": [
      {
        "nome": "Graffio",
        "tipo": {
          "nome": "Normale"
        },
        "potenza": 40,
        "precisione": 100,
        "categoria": "FISICA"
      },
      {
        "nome": "Fiammata",
        "tipo": {
          "nome": "Fuoco"
        },
        "potenza": 90,
        "precisione": 100,
        "categoria": "SPECIALE"
      }
    ]
  },
  {
    "id": "89312bfc-3265-4ad2-9a60-f5f2d73bf82c",
    "specie": {
      "id": "squirtle",
      "nome": "Squirtle",
      "tipi": [
        {
          "nome": "Acqua"
        }
      ],
      "pvBase": 44,
      "attaccoBase": 48,
      "difesaBase": 65,
      "velocitaBase": 43,
      "mosseDisponibili": []
    },
    "livello": 5,
    "esperienza": 0,
    "pvAttuali": 44,
    "mosseApprese": [
      {
        "nome": "Tackle",
        "tipo": {
          "nome": "Normale"
        },
        "potenza": 40,
        "precisione": 100,
        "categoria": "FISICA"
      },
      {
        "nome": "Pistolacqua",
        "tipo": {
          "nome": "Acqua"
        },
        "potenza": 40,
        "precisione": 100,
        "categoria": "SPECIALE"
      }
    ]
  },
  {
    "id": "dba93d48-90e7-478d-85a3-a0a3585b5fe7",
    "specie": {
      "id": "squirtle",
      "nome": "Squirtle",
      "tipi": [
        {
          "nome": "Acqua"
        }
      ],
      "pvBase": 44,
      "attaccoBase": 48,
      "difesaBase": 65,
      "velocitaBase": 43,
      "mosseDisponibili": []
    },
    "livello": 5,
    "esperienza": 0,
    "pvAttuali": 44,
    "mosseApprese": [
      {
        "nome": "Tackle",
        "tipo": {
          "nome": "Normale"
        },
        "potenza": 40,
        "precisione": 100,
        "categoria": "FISICA"
      },
      {
        "nome": "Pistolacqua",
        "tipo": {
          "nome": "Acqua"
        },
        "potenza": 40,
        "precisione": 100,
        "categoria": "SPECIALE"
      }
    ]
  },
  {
    "id": "ffee1e03-a02c-450a-84dc-d17354a3a381",
    "specie": {
      "id": "charmander",
      "nome": "Charmander",
      "tipi": [
        {
          "nome": "Fuoco"
        }
      ],
      "pvBase": 39,
      "attaccoBase": 52,
      "difesaBase": 43,
      "velocitaBase": 65,
      "mosseDisponibili": []
    },
    "livello": 2,
    "esperienza": 0,
    "pvAttuali": 0,
    "mosseApprese": []
  },
  {
    "id": "8e7e92d5-2154-4d51-9ee3-e040196a78c3",
    "specie": {
      "id": "squirtle",
      "nome": "Squirtle",
      "tipi": [
        {
          "nome": "Acqua"
        }
      ],
      "pvBase": 44,
      "attaccoBase": 48,
      "difesaBase": 65,
      "velocitaBase": 43,
      "mosseDisponibili": []
    },
    "livello": 5,
    "esperienza": 0,
    "pvAttuali": 44,
    "mosseApprese": [
      {
        "nome": "Tackle",
        "tipo": {
          "nome": "Normale"
        },
        "potenza": 40,
        "precisione": 100,
        "categoria": "FISICA"
      },
      {
        "nome": "Pistolacqua",
        "tipo": {
          "nome": "Acqua"
        },
        "potenza": 40,
        "precisione": 100,
        "categoria": "SPECIALE"
      }
    ]
  },
  {
    "id": "108563b8-da30-4570-8896-86f265e753ef",
    "specie": {
      "id": "squirtle",
      "nome": "Squirtle",
      "tipi": [
        {
          "nome": "Acqua"
        }
      ],
      "pvBase": 44,
      "attaccoBase": 48,
      "difesaBase": 65,
      "velocitaBase": 43,
      "mosseDisponibili": []
    },
    "livello": 5,
    "esperienza": 0,
    "pvAttuali": 44,
    "mosseApprese": [
      {
        "nome": "Tackle",
        "tipo": {
          "nome": "Normale"
        },
        "potenza": 40,
        "precisione": 100,
        "categoria": "FISICA"
      },
      {
        "nome": "Pistolacqua",
        "tipo": {
          "nome": "Acqua"
        },
        "potenza": 40,
        "precisione": 100,
        "categoria": "SPECIALE"
      }
    ]
  },
  {
    "id": "0ecb275d-5191-45ed-a019-d5e66d31a8a6",
    "specie": {
      "id": "squirtle",
      "nome": "Squirtle",
      "tipi": [
        {
          "nome": "Acqua"
        }
      ],
      "pvBase": 44,
      "attaccoBase": 48,
      "difesaBase": 65,
      "velocitaBase": 43,
      "mosseDisponibili": []
    },
    "livello": 5,
    "esperienza": 0,
    "pvAttuali": 44,
    "mosseApprese": [
      {
        "nome": "Tackle",
        "tipo": {
          "nome": "Normale"
        },
        "potenza": 40,
        "precisione": 100,
        "categoria": "FISICA"
      },
      {
        "nome": "Pistolacqua",
        "tipo": {
          "nome": "Acqua"
        },
        "potenza": 40,
        "precisione": 100,
        "categoria": "SPECIALE"
      }
    ]
  },
  {
    "id": "a9db682d-7060-40e1-b297-51f20d1283bc",
    "specie": {
      "id": "charmander",
      "nome": "Charmander",
      "tipi": [
        {
          "nome": "Fuoco"
        }
      ],
      "pvBase": 39,
      "attaccoBase": 52,
      "difesaBase": 43,
      "velocitaBase": 65,
      "mosseDisponibili": []
    },
    "livello": 5,
    "esperienza": 0,
    "pvAttuali": 39,
    "mosseApprese": [
      {
        "nome": "Graffio",
        "tipo": {
          "nome": "Normale"
        },
        "potenza": 40,
        "precisione": 100,
        "categoria": "FISICA"
      },
      {
        "nome": "Fiammata",
        "tipo": {
          "nome": "Fuoco"
        },
        "potenza": 90,
        "precisione": 100,
        "categoria": "SPECIALE"
      }
    ]
  },
  {
    "id": "7c896ea2-1b69-450f-a6d6-3b6d74ac3c10",
    "specie": {
      "id": "charmander",
      "nome": "Charmander",
      "tipi": [
        {
          "nome": "Fuoco"
        }
      ],
      "pvBase": 39,
      "attaccoBase": 52,
      "difesaBase": 43,
      "velocitaBase": 65,
      "mosseDisponibili": []
    },
    "livello": 3,
    "esperienza": 0,
    "pvAttuali": 0,
    "mosseApprese": [
      {
        "nome": "Braciere",
        "tipo": {
          "nome": "Fuoco"
        },
        "potenza": 10,
        "precisione": 100,
        "categoria": "SPECIALE"
      }
    ]
  },
  {
    "id": "1001061d-b905-445c-a632-3dff79f5f61d",
    "specie": {
      "id": "bulbasaur",
      "nome": "Bulbasaur",
      "tipi": [
        {
          "nome": "Erba"
        }
      ],
      "pvBase": 45,
      "attaccoBase": 49,
      "difesaBase": 49,
      "velocitaBase": 45,
      "mosseDisponibili": []
    },
    "livello": 3,
    "esperienza": 0,
    "pvAttuali": 0,
    "mosseApprese": [
      {
        "nome": "Fogliolina",
        "tipo": {
          "nome": "Erba"
        },
        "potenza": 10,
        "precisione": 100,
        "categoria": "SPECIALE"
      }
    ]
  },
  {
    "id": "920b2856-df5a-44a9-ba30-b37e97bc901c",
    "specie": {
      "id": "bulbasaur",
      "nome": "Bulbasaur",
      "tipi": [
        {
          "nome": "Erba"
        }
      ],
      "pvBase": 45,
      "attaccoBase": 49,
      "difesaBase": 49,
      "velocitaBase": 45,
      "mosseDisponibili": []
    },
    "livello": 3,
    "esperienza": 0,
    "pvAttuali": 0,
    "mosseApprese": [
      {
        "nome": "Fogliolina",
        "tipo": {
          "nome": "Erba"
        },
        "potenza": 10,
        "precisione": 100,
        "categoria": "SPECIALE"
      }
    ]
  },
  {
    "id": "1906cb72-0e1c-44ef-847c-0677a149c1d6",
    "specie": {
      "id": "bulbasaur",
      "nome": "Bulbasaur",
      "tipi": [
        {
          "nome": "Erba"
        }
      ],
      "pvBase": 45,
      "attaccoBase": 49,
      "difesaBase": 49,
      "velocitaBase": 45,
      "mosseDisponibili": []
    },
    "livello": 5,
    "esperienza": 0,
    "pvAttuali": 0,
    "mosseApprese": [
      {
        "nome": "Fogliolina",
        "tipo": {
          "nome": "Erba"
        },
        "potenza": 10,
        "precisione": 100,
        "categoria": "SPECIALE"
      }
    ]
  }
]